[
{
  "url": "https://www.coindesk.com/pt-br/latest-crypto-news",
  "scraped_at": "2025-12-05T01:53:36.871982",
  "primeira_noticia": {
    "titulo": "Mercados",
    "resumo": "Veja Quanto Bitcoin, XRP, Ether e Solana Podem Oscilar com o Relatório de Inflação desta Sexta-feira",
    "resumo2": "Um relatório de inflação mais brando pode reduzir o rendimento dos títulos do Tesouro de 10 anos e apoiar as criptomoedas.",
    "link": "https://www.coindesk.com/pt-br/markets/2025/12/05/here-s-how-much-btc-eth-sol-xrp-may-move-on-friday-s-inflation-report"
  }
}
]